Metadata-Version: 2.1
Name: TTS
Version: 0.21.3
Summary: Deep learning for Text to Speech by Coqui.
Home-page: https://github.com/coqui-ai/TTS
Author: Eren Gölge
Author-email: egolge@coqui.ai
License: MPL-2.0
Project-URL: Documentation, https://github.com/coqui-ai/TTS/wiki
Project-URL: Tracker, https://github.com/coqui-ai/TTS/issues
Project-URL: Repository, https://github.com/coqui-ai/TTS
Project-URL: Discussions, https://github.com/coqui-ai/TTS/discussions
Classifier: Programming Language :: Python
Classifier: Programming Language :: Python :: 3
Classifier: Programming Language :: Python :: 3.9
Classifier: Programming Language :: Python :: 3.10
Classifier: Programming Language :: Python :: 3.11
Classifier: Development Status :: 3 - Alpha
Classifier: Intended Audience :: Science/Research
Classifier: Intended Audience :: Developers
Classifier: Operating System :: POSIX :: Linux
Classifier: License :: OSI Approved :: Mozilla Public License 2.0 (MPL 2.0)
Classifier: Topic :: Software Development
Classifier: Topic :: Software Development :: Libraries :: Python Modules
Classifier: Topic :: Multimedia :: Sound/Audio :: Speech
Classifier: Topic :: Multimedia :: Sound/Audio
Classifier: Topic :: Multimedia
Classifier: Topic :: Scientific/Engineering :: Artificial Intelligence
Requires-Python: >=3.9.0, <3.12
License-File: LICENSE.txt
Requires-Dist: cython >=0.29.30
Requires-Dist: scipy >=1.11.2
Requires-Dist: torch >=2.1
Requires-Dist: torchaudio
Requires-Dist: soundfile >=0.12.0
Requires-Dist: librosa >=0.10.0
Requires-Dist: scikit-learn >=1.3.0
Requires-Dist: inflect >=5.6.0
Requires-Dist: tqdm >=4.64.1
Requires-Dist: anyascii >=0.3.0
Requires-Dist: pyyaml >=6.0
Requires-Dist: fsspec >=2023.6.0
Requires-Dist: aiohttp >=3.8.1
Requires-Dist: packaging >=23.1
Requires-Dist: flask >=2.0.1
Requires-Dist: pysbd >=0.3.4
Requires-Dist: umap-learn >=0.5.1
Requires-Dist: pandas <2.0,>=1.4
Requires-Dist: matplotlib >=3.7.0
Requires-Dist: trainer >=0.0.32
Requires-Dist: coqpit >=0.0.16
Requires-Dist: jieba
Requires-Dist: pypinyin
Requires-Dist: hangul-romanize
Requires-Dist: gruut[de,es,fr] ==2.2.3
Requires-Dist: jamo
Requires-Dist: nltk
Requires-Dist: g2pkk >=0.1.1
Requires-Dist: bangla
Requires-Dist: bnnumerizer
Requires-Dist: bnunicodenormalizer
Requires-Dist: einops >=0.6.0
Requires-Dist: transformers >=4.33.0
Requires-Dist: encodec >=0.1.1
Requires-Dist: unidecode >=1.3.2
Requires-Dist: num2words
Requires-Dist: spacy[ja] >=3
Requires-Dist: numba ==0.55.1 ; python_version < "3.9"
Requires-Dist: numpy ==1.22.0 ; python_version <= "3.10"
Requires-Dist: numpy >=1.24.3 ; python_version > "3.10"
Requires-Dist: numba >=0.57.0 ; python_version >= "3.9"
Provides-Extra: all
Requires-Dist: black ; extra == 'all'
Requires-Dist: coverage ; extra == 'all'
Requires-Dist: isort ; extra == 'all'
Requires-Dist: nose2 ; extra == 'all'
Requires-Dist: pylint ==2.10.2 ; extra == 'all'
Requires-Dist: bokeh ==1.4.0 ; extra == 'all'
Requires-Dist: mecab-python3 ==1.0.6 ; extra == 'all'
Requires-Dist: unidic-lite ==1.0.8 ; extra == 'all'
Requires-Dist: cutlet ; extra == 'all'
Provides-Extra: dev
Requires-Dist: black ; extra == 'dev'
Requires-Dist: coverage ; extra == 'dev'
Requires-Dist: isort ; extra == 'dev'
Requires-Dist: nose2 ; extra == 'dev'
Requires-Dist: pylint ==2.10.2 ; extra == 'dev'
Provides-Extra: ja
Requires-Dist: mecab-python3 ==1.0.6 ; extra == 'ja'
Requires-Dist: unidic-lite ==1.0.8 ; extra == 'ja'
Requires-Dist: cutlet ; extra == 'ja'
Provides-Extra: notebooks
Requires-Dist: bokeh ==1.4.0 ; extra == 'notebooks'
